stela_toolkit/__init__.py
stela_toolkit/_check_inputs.py
stela_toolkit/_clarify_warnings.py
stela_toolkit/coherence.py
stela_toolkit/cross_correlation.py
stela_toolkit/cross_spectrum.py
stela_toolkit/data_loader.py
stela_toolkit/data_simulator.py
stela_toolkit/frequency_binning.py
stela_toolkit/gaussian_process.py
stela_toolkit/lag_energy_spectrum.py
stela_toolkit/lag_frequency_spectrum.py
stela_toolkit/plot.py
stela_toolkit/power_spectrum.py
stela_toolkit/preprocessing.py
stela_toolkit-0.4.3.dist-info/licenses/LICENSE
stela_toolkit-0.4.3.dist-info/METADATA
stela_toolkit-0.4.3.dist-info/WHEEL
stela_toolkit-0.4.3.dist-info/top_level.txt
stela_toolkit-0.4.3.dist-info/RECORD
