Metadata-Version: 2.4
Name: stela-toolkit
Version: 0.4.3
Summary: A Python package for interpolating astrophysical light curves using Gaussian Processes (more ML models to come!) in order to compute frequency-domain and standard time domain data products.
Author-email: Collin Lewin <clewin@mit.edu>
License-Expression: MIT
Project-URL: Homepage, https://github.com/collinlewin/STELA-Toolkit
Project-URL: Documentation, https://collinlewin.github.io/STELA-Toolkit/
Requires-Python: >=3.8
License-File: LICENSE
Requires-Dist: numpy<2.0,>=1.20
Requires-Dist: scipy>=1.7
Requires-Dist: matplotlib>=3.5
Requires-Dist: astropy>=5.0
Requires-Dist: torch>=1.10
Requires-Dist: gpytorch>=1.9
Requires-Dist: statsmodels>=0.13
Dynamic: license-file
